terminusgps/__init__.py
terminusgps/default_settings.py
terminusgps/mixins.py
terminusgps/validators.py
terminusgps/authorizenet/__init__.py
terminusgps/authorizenet/constants.py
terminusgps/authorizenet/service.py
terminusgps/authorizenet/api/__init__.py
terminusgps/authorizenet/api/address_profiles.py
terminusgps/authorizenet/api/customer_profiles.py
terminusgps/authorizenet/api/payment_profiles.py
terminusgps/authorizenet/api/subscriptions.py
terminusgps/authorizenet/api/transactions.py
terminusgps/wialon/__init__.py
terminusgps/wialon/constants.py
terminusgps/wialon/flags.py
terminusgps/wialon/session.py
terminusgps/wialon/utils.py
python_terminusgps-50.3.1.dist-info/METADATA
python_terminusgps-50.3.1.dist-info/WHEEL
python_terminusgps-50.3.1.dist-info/licenses/COPYING
python_terminusgps-50.3.1.dist-info/RECORD
