Metadata-Version: 2.4
Name: python-terminusgps
Version: 50.3.1
Summary: Provides abstractions/utilities for working with Wialon API, Authorize.NET API, AWS API, and more.
Project-URL: Documentation, https://terminusgps.github.io/python-terminusgps
Project-URL: Repository, https://github.com/terminusgps/python-terminusgps
Author-email: Blake Nall <blake@terminusgps.com>
License-File: COPYING
Classifier: License :: OSI Approved :: GNU General Public License v3 or later (GPLv3+)
Classifier: Operating System :: OS Independent
Classifier: Programming Language :: Python :: 3
Classifier: Programming Language :: Python :: 3.12
Requires-Python: >=3.12
Requires-Dist: authorizenet>=1.1.5
Requires-Dist: django>=5.2.7
Requires-Dist: py-aiowialon>=1.3.5
Requires-Dist: python-wialon>=1.2.4
